MANIFEST.in
README.md
requirements.txt
setup.py
monitoring_db_license_generator/__init__.py
monitoring_db_license_generator/app.py
monitoring_db_license_generator.egg-info/PKG-INFO
monitoring_db_license_generator.egg-info/SOURCES.txt
monitoring_db_license_generator.egg-info/dependency_links.txt
monitoring_db_license_generator.egg-info/entry_points.txt
monitoring_db_license_generator.egg-info/not-zip-safe
monitoring_db_license_generator.egg-info/requires.txt
monitoring_db_license_generator.egg-info/top_level.txt
monitoring_db_license_generator/endpoints/__init__.py
monitoring_db_license_generator/endpoints/health.py
monitoring_db_license_generator/logic/__init__.py
monitoring_db_license_generator/logic/create_licenses.py
monitoring_db_license_generator/models/__init__.py
monitoring_db_license_generator/settings/__init__.py
monitoring_db_license_generator/settings/service_settings.py