Metadata-Version: 1.0
Name: monitoring-db-license-generator
Version: 0.0.1
Summary: monitoring_db_license_generator service
Home-page: UNKNOWN
Author: UNKNOWN
Author-email: UNKNOWN
License: UNKNOWN
Platform: UNKNOWN
